{"iutodrf1cmti065kn7fes0acn4":{"salt":"iutodrf1cmti065kn7fes0acn4","user_id":"global"},"0505ucpcniv5qqi1h56ejrn2bg":{"salt":"0505ucpcniv5qqi1h56ejrn2bg"},"4jb569q5u7d4nsom03jm2dtlpa":{"salt":"4jb569q5u7d4nsom03jm2dtlpa","user_id":"global"},"c1qla6ak4qa4gla87nfoba7ub7":{"salt":"c1qla6ak4qa4gla87nfoba7ub7","user_id":"global"},"q9lhk0fhmeuv6000qvv0hiqn1k":{"salt":"q9lhk0fhmeuv6000qvv0hiqn1k","user_id":"global"},"7t7sq8aj96njh9q80svhbn8buo":{"salt":"7t7sq8aj96njh9q80svhbn8buo","user_id":"global"},"4pdv0av4997mjeoaatuonv6ru2":{"salt":"4pdv0av4997mjeoaatuonv6ru2","user_id":"global"},"31gucphfnl71e748h18d25io3q":{"salt":"31gucphfnl71e748h18d25io3q","user_id":"global"},"gsl0v88feb7mm6pl20m6pp042l":{"salt":"gsl0v88feb7mm6pl20m6pp042l","user_id":"global"},"92t91193p8j7tbk308g41rrmjr":{"salt":"92t91193p8j7tbk308g41rrmjr","user_id":"global"},"uuho3tpkef4uu8cbsq96jk95ij":{"salt":"uuho3tpkef4uu8cbsq96jk95ij","user_id":"global"},"p25bdr7676gb6kdt59r2nn9inq":{"salt":"p25bdr7676gb6kdt59r2nn9inq","user_id":"global"},"efpcf93gi59dpldgmcpc7jm2qq":{"salt":"efpcf93gi59dpldgmcpc7jm2qq","user_id":"global"},"l3lftv6ktavejav6pm2elfihqo":{"salt":"l3lftv6ktavejav6pm2elfihqo","user_id":"global"},"l24pdhmc6a34pnl6b08kn13si4":{"salt":"l24pdhmc6a34pnl6b08kn13si4","user_id":"global"},"kulmtdvlue2jrr1hfhucimuuon":{"salt":"kulmtdvlue2jrr1hfhucimuuon","user_id":"global"},"oli1ro1b3l63vsclfvl440lj0t":{"salt":"oli1ro1b3l63vsclfvl440lj0t","user_id":"global"},"aubgjflik5es75pna2u4s5hkdl":{"salt":"aubgjflik5es75pna2u4s5hkdl","user_id":"global"},"qruu4hpclvdh2v3go32d1aof8e":{"salt":"qruu4hpclvdh2v3go32d1aof8e","user_id":"global"},"lhokjsch3sk9sd53uk1l2dlkhn":{"salt":"lhokjsch3sk9sd53uk1l2dlkhn","user_id":"global"},"trb0h70d4nglq4emdhcq2okvdu":{"salt":"trb0h70d4nglq4emdhcq2okvdu","user_id":"global"},"k4srgcf7amvgfrcaneli6uj2cn":{"salt":"k4srgcf7amvgfrcaneli6uj2cn","user_id":"global"},"pt7cnk55c5edf1lodp53ppo8st":{"salt":"pt7cnk55c5edf1lodp53ppo8st","user_id":"global"},"59hui2n7gtb0igfnt83pnj2lni":{"salt":"59hui2n7gtb0igfnt83pnj2lni","user_id":"global"},"qg2n0gbc4cbralrmc2lmf2uf2o":{"salt":"qg2n0gbc4cbralrmc2lmf2uf2o","user_id":"global"},"q5rn17lepqj523e0nseali16ep":{"salt":"q5rn17lepqj523e0nseali16ep","user_id":"global"},"0fbjnbip06v7l9hhl127neanfn":{"salt":"0fbjnbip06v7l9hhl127neanfn","user_id":"global"},"q2qefkiuoj0enfkhlsrvsee1om":{"salt":"q2qefkiuoj0enfkhlsrvsee1om","user_id":"global"},"qlp5139esp5hgbk43vnmu89m1c":{"salt":"qlp5139esp5hgbk43vnmu89m1c","user_id":"global"},"68ujvra4bmmhfjqrbrou0ku31s":{"salt":"68ujvra4bmmhfjqrbrou0ku31s","user_id":"global"},"gdu3cbp884cad5otu84edov4ha":{"salt":"gdu3cbp884cad5otu84edov4ha","user_id":"global"},"bmfvl52oip7jcmhd6rt2tkkp5p":{"salt":"bmfvl52oip7jcmhd6rt2tkkp5p","user_id":"global"},"ic27proi0fqhs84cm713v37ve0":{"salt":"ic27proi0fqhs84cm713v37ve0","user_id":"global"},"veqk5g3ohduo20p1fit52bkqmu":{"salt":"veqk5g3ohduo20p1fit52bkqmu","user_id":"global"},"c3pbfud4q7mvb7l7a6cuei4ep7":{"salt":"c3pbfud4q7mvb7l7a6cuei4ep7","user_id":"global"},"j54dan7f64ps65ccvgngkm6mii":{"salt":"j54dan7f64ps65ccvgngkm6mii","user_id":"global"},"vlge9l1umqp2s6jk81gvupkokg":{"salt":"vlge9l1umqp2s6jk81gvupkokg","user_id":"global"},"dlfmokrkqstapk5dq3jj7kk15v":{"salt":"dlfmokrkqstapk5dq3jj7kk15v","user_id":"global"},"2br09dlahkj1diogoc5vip7ql1":{"salt":"2br09dlahkj1diogoc5vip7ql1","user_id":"global"},"i1dvp968odpl9h4g95v19hs1co":{"salt":"i1dvp968odpl9h4g95v19hs1co","user_id":"global"},"0ul88kl512shjc4g5d3n1nvnbj":{"salt":"0ul88kl512shjc4g5d3n1nvnbj","user_id":"global"},"inl6p4vq8253k7ptli1na63vdt":{"salt":"inl6p4vq8253k7ptli1na63vdt","user_id":"global"},"lestdh6kkdlrptoq2j4i8fgn4r":{"salt":"lestdh6kkdlrptoq2j4i8fgn4r","user_id":"global"},"mc7bgjkdc9i1sso5b7lmahrfja":{"salt":"mc7bgjkdc9i1sso5b7lmahrfja","user_id":"global"},"3mr63gmrv3i90vr7qj1rb3mlja":{"salt":"3mr63gmrv3i90vr7qj1rb3mlja","user_id":"global"},"n9icpbfpbusvkitgn8s0jrlvo1":{"salt":"n9icpbfpbusvkitgn8s0jrlvo1","user_id":"global"},"vql0t0g2gl8q1ll40aaaqvvuec":{"salt":"vql0t0g2gl8q1ll40aaaqvvuec","user_id":"global"},"o7oaqc1ptf6fjr889prm1qdda5":{"salt":"o7oaqc1ptf6fjr889prm1qdda5","user_id":"global"},"q7cd06s67cas843ea5ld2vkc7e":{"salt":"q7cd06s67cas843ea5ld2vkc7e","user_id":"global"},"smir1lmhetfmd0fn98roagp47u":{"salt":"smir1lmhetfmd0fn98roagp47u","user_id":"global"},"5ohfe5pi7k9cmqu288sebeg887":{"salt":"5ohfe5pi7k9cmqu288sebeg887","user_id":"global"},"hp3c53pvh5791uj4tseigijll3":{"salt":"hp3c53pvh5791uj4tseigijll3","user_id":"global"},"8qr8f77qjtsaomgqjnrosn1dqq":{"salt":"8qr8f77qjtsaomgqjnrosn1dqq","user_id":"global"},"34obok6c89o42ok8jivm07ui7u":{"salt":"34obok6c89o42ok8jivm07ui7u","user_id":"global"},"5o5oaufodkukn1aq4lvikrrhle":{"salt":"5o5oaufodkukn1aq4lvikrrhle","user_id":"global"},"fj87mq6vflmvtjmkhrdgt32l2i":{"salt":"fj87mq6vflmvtjmkhrdgt32l2i","user_id":"global"},"gha5a83ter6sqls4sk9gli37rp":{"salt":"gha5a83ter6sqls4sk9gli37rp","user_id":"global"},"1n5sj7qj13mudglfivrc4lg8r7":{"salt":"1n5sj7qj13mudglfivrc4lg8r7","user_id":"global"},"4qag8qdh2ucn9j402e5f3cfdph":{"salt":"4qag8qdh2ucn9j402e5f3cfdph","user_id":"global"},"rq4emt92rle2jhoi4aooupceqb":{"salt":"rq4emt92rle2jhoi4aooupceqb","user_id":"global"},"vpaehi9e1uds3l4bl9j1onetdb":{"salt":"vpaehi9e1uds3l4bl9j1onetdb","user_id":"global"},"kq16mecuhi2qe76kqs6akr8o84":{"salt":"kq16mecuhi2qe76kqs6akr8o84","user_id":"global"},"kjbk9d589hc4ahkc3e5vqf8i3c":{"salt":"kjbk9d589hc4ahkc3e5vqf8i3c","user_id":"global"},"90qk5ji5fu6jfbn50lt4o6agpo":{"salt":"90qk5ji5fu6jfbn50lt4o6agpo","user_id":"global"},"u9ao3rmso2g3979sqmq83853pn":{"salt":"u9ao3rmso2g3979sqmq83853pn","user_id":"global"},"2bgn4914qut6nudqt86hne3p8s":{"salt":"2bgn4914qut6nudqt86hne3p8s","user_id":"global"},"d7c84s22beh07mvtudv0s43tm9":{"salt":"d7c84s22beh07mvtudv0s43tm9","user_id":"global"},"ti5ffgv80cull2h124qkb6cvlu":{"salt":"ti5ffgv80cull2h124qkb6cvlu","user_id":"global"},"mqjglut43vip3t4hku3o9n49bv":{"salt":"mqjglut43vip3t4hku3o9n49bv","user_id":"global"},"o3r3v26uop2e1raqmtbfavq9ak":{"salt":"o3r3v26uop2e1raqmtbfavq9ak","user_id":"global"},"js4ul4nchf15k0lkr2ctlvnn2b":{"salt":"js4ul4nchf15k0lkr2ctlvnn2b","user_id":"global"},"rprkvj1gfccqng9h58j8khiqfq":{"salt":"rprkvj1gfccqng9h58j8khiqfq","user_id":"global"},"tropl7mm3fo32kdbt674f0m6gm":{"salt":"tropl7mm3fo32kdbt674f0m6gm","user_id":"global"},"9rvthngiqdj4ium23nb57fpuaf":{"salt":"9rvthngiqdj4ium23nb57fpuaf","user_id":"global"},"02qf624c07ei7nirqc1ope25oe":{"salt":"02qf624c07ei7nirqc1ope25oe","user_id":"global"},"n6lntcou4frm5idu65n3fqumd0":{"salt":"n6lntcou4frm5idu65n3fqumd0","user_id":"global"},"of27ac60pspkvtbiq0srg683s2":{"salt":"of27ac60pspkvtbiq0srg683s2","user_id":"global"},"ogo4jku0kr81mrhq7dpusr98u9":{"salt":"ogo4jku0kr81mrhq7dpusr98u9","user_id":"global"},"21u7sh9go2549m0m0simp6rfmv":{"salt":"21u7sh9go2549m0m0simp6rfmv","user_id":"global"},"q0khp87ekf6j7dt4gfeh9bl332":{"salt":"q0khp87ekf6j7dt4gfeh9bl332","user_id":"global"},"se9egrbs4ikm4rcuiah3h5vjtg":{"salt":"se9egrbs4ikm4rcuiah3h5vjtg","user_id":"global"},"83iqnl2eq6oqutbg6aopb2fulb":{"salt":"83iqnl2eq6oqutbg6aopb2fulb","user_id":"global"},"drp1gnhuc8umes9u9n8dk40rn3":{"salt":"drp1gnhuc8umes9u9n8dk40rn3","user_id":"global"},"kot64q4gqgafdt20f8mlgk1dvm":{"salt":"kot64q4gqgafdt20f8mlgk1dvm","user_id":"global"},"4s1tgoao49npak1q4c2m1gk4ms":{"salt":"4s1tgoao49npak1q4c2m1gk4ms","user_id":"global"},"3a3pkahgq3c5dgpen2l7sjqlvk":{"salt":"3a3pkahgq3c5dgpen2l7sjqlvk","user_id":"global"},"qhb716pdbtm5263d48bqd7tkb8":{"salt":"qhb716pdbtm5263d48bqd7tkb8","user_id":"global"},"tovv7ev78sgg0hkfah5m0s5gqq":{"salt":"tovv7ev78sgg0hkfah5m0s5gqq","user_id":"global"},"rv40vpd8mttnme5oedrd9aceaq":{"salt":"rv40vpd8mttnme5oedrd9aceaq","user_id":"global"},"02t2s9vahrtedq3lmel9p2pmn7":{"salt":"02t2s9vahrtedq3lmel9p2pmn7","user_id":"global"},"4vqtu8q1fgrmli7h466apg808i":{"salt":"4vqtu8q1fgrmli7h466apg808i","user_id":"global"},"kosm9u85jvi36nka35415f0moi":{"salt":"kosm9u85jvi36nka35415f0moi","user_id":"global"},"ap2003l7cii9oedjkhg4852mrk":{"salt":"ap2003l7cii9oedjkhg4852mrk","user_id":"global"},"uibcmitsiqo47u9gc25l6t2gt1":{"salt":"uibcmitsiqo47u9gc25l6t2gt1","user_id":"global"},"0v2lmh35ui09p428bt445pk1r4":{"salt":"0v2lmh35ui09p428bt445pk1r4","user_id":"global"},"nf0dtn1jkc97h20hf1mrdvsc7t":{"salt":"nf0dtn1jkc97h20hf1mrdvsc7t","user_id":"global"},"2eda2b6ebq78nthflbcqs7968v":{"salt":"2eda2b6ebq78nthflbcqs7968v","user_id":"global"},"9mnnlbl0rivu10jnfjlo4blp6a":{"salt":"9mnnlbl0rivu10jnfjlo4blp6a","user_id":"global"},"d3f1obe0eadqcmomcaph2ltoh0":{"salt":"d3f1obe0eadqcmomcaph2ltoh0","user_id":"global"},"bfimid2mkcuhsaa805v4pshke6":{"salt":"bfimid2mkcuhsaa805v4pshke6","user_id":"global"},"cv18i1advf1q9ek0r222um3qcv":{"salt":"cv18i1advf1q9ek0r222um3qcv","user_id":"global"},"09lj76n2n0ip93j4neft202vfs":{"salt":"09lj76n2n0ip93j4neft202vfs","user_id":"global"},"trdql213nfe178ctdp355a13nd":{"salt":"trdql213nfe178ctdp355a13nd","user_id":"global"},"cbljqpq2v0bb3p5uqr993frj35":{"salt":"cbljqpq2v0bb3p5uqr993frj35","user_id":"global"},"1ththuu533uamflbpuq0bhs32o":{"salt":"1ththuu533uamflbpuq0bhs32o","user_id":"global"},"b4us0ohntht242l5gk99rna6hj":{"salt":"b4us0ohntht242l5gk99rna6hj","user_id":"global"},"c62hm77pv01n4jtkesbma266s9":{"salt":"c62hm77pv01n4jtkesbma266s9","user_id":"global"},"rdpqlijh8qe3v015go3ijpsipo":{"salt":"rdpqlijh8qe3v015go3ijpsipo","user_id":"global"},"1s65s44vtbf81330au6umqugpf":{"salt":"1s65s44vtbf81330au6umqugpf","user_id":"global"},"rq32st2dfr18dptvq9gcclvi8j":{"salt":"rq32st2dfr18dptvq9gcclvi8j","user_id":"global"},"jvkeh8caor5d221rqoe5hkmlpk":{"salt":"jvkeh8caor5d221rqoe5hkmlpk","user_id":"global"},"fbb7lv6vvm269i14iif3pb2qnt":{"salt":"fbb7lv6vvm269i14iif3pb2qnt","user_id":"global"},"l7anfct7akmo18lum3j4imr9g4":{"salt":"l7anfct7akmo18lum3j4imr9g4","user_id":"global"},"89bf9qs3iq46cb58etgjr9mjik":{"salt":"89bf9qs3iq46cb58etgjr9mjik","user_id":"global"},"q3251lspncctuuoq96tdj3qckr":{"salt":"q3251lspncctuuoq96tdj3qckr","user_id":"global"},"1ho0engpd1q24tbnhl6el8vrb8":{"salt":"1ho0engpd1q24tbnhl6el8vrb8","user_id":"global"},"de9200rcsu8mjmub63g8o61etb":{"salt":"de9200rcsu8mjmub63g8o61etb","user_id":"global"},"k1as125sdah755qkqdi7iha36c":{"salt":"k1as125sdah755qkqdi7iha36c","user_id":"global"},"1acmn73nhk66omuo6mb3gjm63a":{"salt":"1acmn73nhk66omuo6mb3gjm63a","user_id":"global"},"mdmechnv4o328830o9sduhhph0":{"salt":"mdmechnv4o328830o9sduhhph0","user_id":"global"},"gmg4e2qbbldbl9mfbubms39uah":{"salt":"gmg4e2qbbldbl9mfbubms39uah","user_id":"global"},"4k2jn4uqsiuarl3mvel8dsvdit":{"salt":"4k2jn4uqsiuarl3mvel8dsvdit","user_id":"global"},"b8vgcsd3pja63gegs48g210vp1":{"salt":"b8vgcsd3pja63gegs48g210vp1","user_id":"global"},"96spapahpc51rg0p7vsnq13vs1":{"salt":"96spapahpc51rg0p7vsnq13vs1","user_id":"global"},"stpai4rumece1oqdlvgp6nt1t4":{"salt":"stpai4rumece1oqdlvgp6nt1t4","user_id":"global"},"7c6gku8880klkjhm3m34vr9r3a":{"salt":"7c6gku8880klkjhm3m34vr9r3a","user_id":"global"},"0dfp7ti08b6ch9f2doqolal794":{"salt":"0dfp7ti08b6ch9f2doqolal794","user_id":"global"},"vvf628hsj8686s90o5h9s51el1":{"salt":"vvf628hsj8686s90o5h9s51el1","user_id":"global"},"l64vgvlrj3iiddoup74ibn4cnq":{"salt":"l64vgvlrj3iiddoup74ibn4cnq","user_id":"global"},"tdrdhvfiinhlrlpil4jh9j83ql":{"salt":"tdrdhvfiinhlrlpil4jh9j83ql","user_id":"global"},"3nsvp845tficomkqf7u5o41a60":{"salt":"3nsvp845tficomkqf7u5o41a60","user_id":"global"},"mgfbpkn853s10dhicfpj4sinj3":{"salt":"mgfbpkn853s10dhicfpj4sinj3","user_id":"global"},"oskj4o6gbnv1dm55usfkp6r9eu":{"salt":"oskj4o6gbnv1dm55usfkp6r9eu","user_id":"global"},"nm317ojclr8ldbeiaenoa5gnag":{"salt":"nm317ojclr8ldbeiaenoa5gnag","user_id":"global"},"s3vf2qle7i9kdm4971j8ibttis":{"salt":"s3vf2qle7i9kdm4971j8ibttis","user_id":"global"},"ckgdeikbgr0utgpfkdakvar4d5":{"salt":"ckgdeikbgr0utgpfkdakvar4d5","user_id":"global"},"6e0p2fefj6fu8dufoacqiasfbt":{"salt":"6e0p2fefj6fu8dufoacqiasfbt","user_id":"global"},"jgdojrpkt85jukruaj9gec4hlg":{"salt":"jgdojrpkt85jukruaj9gec4hlg","user_id":"global"},"q78kc8adihh3siu23p8i4apl8n":{"salt":"q78kc8adihh3siu23p8i4apl8n","user_id":"global"},"m7tgio5if3u6hfusm060jloh8o":{"salt":"m7tgio5if3u6hfusm060jloh8o","user_id":"global"},"buocra1ccf0t8o0dbdefvqmpi6":{"salt":"buocra1ccf0t8o0dbdefvqmpi6","user_id":"global"},"1nu00g91kk0c7efilo05c9salv":{"salt":"1nu00g91kk0c7efilo05c9salv","user_id":"global"},"6lt9j5bbek7obfg4kjir14q576":{"salt":"6lt9j5bbek7obfg4kjir14q576","user_id":"global"},"3vh82diurvlde3mlagd8mu10n3":{"salt":"3vh82diurvlde3mlagd8mu10n3","user_id":"global"},"9dap4u64dd5q3auj4lp70vsn07":{"salt":"9dap4u64dd5q3auj4lp70vsn07","user_id":"global"},"mb9b2fo15057ids2p14j1s2065":{"salt":"mb9b2fo15057ids2p14j1s2065","user_id":"global"},"3geb465iiaedqi3jjn7fem31lb":{"salt":"3geb465iiaedqi3jjn7fem31lb","user_id":"global"},"ua7nnmng1ldc3d2uldndnjqgs2":{"salt":"ua7nnmng1ldc3d2uldndnjqgs2","user_id":"global"},"p1nea9slkl7brg21gg9p7qikv8":{"salt":"p1nea9slkl7brg21gg9p7qikv8","user_id":"global"},"qsta9ed3lr807f19oabchef9du":{"salt":"qsta9ed3lr807f19oabchef9du","user_id":"global"},"70qqpbcopo1o7toa85svdeovhk":{"salt":"70qqpbcopo1o7toa85svdeovhk","user_id":"global"},"0qas4e2vuor0pt99u0s4scj3db":{"salt":"0qas4e2vuor0pt99u0s4scj3db","user_id":"global"},"uuj8jgnc8jvmps1nc8gsi0k8hk":{"salt":"uuj8jgnc8jvmps1nc8gsi0k8hk","user_id":"global"},"kfvaqf0j2s87rdrqsbatd8aa3e":{"salt":"kfvaqf0j2s87rdrqsbatd8aa3e","user_id":"global"},"1decm1tjumltlgvqgtj46b94bd":{"salt":"1decm1tjumltlgvqgtj46b94bd","user_id":"global"},"chfsvhql7be9ie0r28u16smqfc":{"salt":"chfsvhql7be9ie0r28u16smqfc","user_id":"global"},"d8efluukecnsn9ljf0hao3oho2":{"salt":"d8efluukecnsn9ljf0hao3oho2","user_id":"global"},"ivi1dsf82f8i0bhnd6i52hbabg":{"salt":"ivi1dsf82f8i0bhnd6i52hbabg","user_id":"global"},"7r3plndiv4ae78bkjll6e0uk16":{"salt":"7r3plndiv4ae78bkjll6e0uk16","user_id":"global"},"1mjf7tv6cbd60u7m0uhjd98f00":{"salt":"1mjf7tv6cbd60u7m0uhjd98f00","user_id":"global"},"7icg4rcqq88rnd7g28irfo4v27":{"salt":"7icg4rcqq88rnd7g28irfo4v27","user_id":"global"},"contlu9hnn2bf0r49pn29udol6":{"salt":"contlu9hnn2bf0r49pn29udol6","user_id":"global"},"os8jmtjocafese1hqbmac489vp":{"salt":"os8jmtjocafese1hqbmac489vp","user_id":"global"},"5j0bm1us8bou5107bjql7917uc":{"salt":"5j0bm1us8bou5107bjql7917uc","user_id":"global"},"1m8tchmnfv4fa32g3jfvp892di":{"salt":"1m8tchmnfv4fa32g3jfvp892di","user_id":"global"},"qag4lt9ofcq1kaq9amujqr4ngt":{"salt":"qag4lt9ofcq1kaq9amujqr4ngt","user_id":"global"},"e8jn7uboei6t5tlead6so782oj":{"salt":"e8jn7uboei6t5tlead6so782oj","user_id":"global"},"nfak8k1d93okgtshj5nml7peqj":{"salt":"nfak8k1d93okgtshj5nml7peqj","user_id":"global"},"lhmtdbljn8r4pa8piq3trkostn":{"salt":"lhmtdbljn8r4pa8piq3trkostn","user_id":"global"},"g57b6n0b3sms1g877jcovdgb8o":{"salt":"g57b6n0b3sms1g877jcovdgb8o","user_id":"global"},"6e709bbcvi2d0dgk43g3ljre70":{"salt":"6e709bbcvi2d0dgk43g3ljre70","user_id":"global"},"i1elue7fs24u5ilokaks6jii2u":{"salt":"i1elue7fs24u5ilokaks6jii2u","user_id":"global"},"b7unodip72kdaiu1pnfabudhis":{"salt":"b7unodip72kdaiu1pnfabudhis","user_id":"global"},"n5s4l7gkged6lv8ua1adcoquau":{"salt":"n5s4l7gkged6lv8ua1adcoquau","user_id":"global"},"u4e68t1eisk2dvggemm2au4151":{"salt":"u4e68t1eisk2dvggemm2au4151","user_id":"global"},"0f7jfb715p92o4bdnbl5nquvp4":{"salt":"0f7jfb715p92o4bdnbl5nquvp4","user_id":"global"},"ahjulphgor1v5e39knd04i84hn":{"salt":"ahjulphgor1v5e39knd04i84hn","user_id":"global"},"4fn7gguufsoe380jmrjeliut09":{"salt":"4fn7gguufsoe380jmrjeliut09","user_id":"global"},"t5u7arcvm7ssbsl9l3rfopun1v":{"salt":"t5u7arcvm7ssbsl9l3rfopun1v","user_id":"global"},"pjjpup686re3sjsc8id05ip2fp":{"salt":"pjjpup686re3sjsc8id05ip2fp","user_id":"global"},"410ulcaos6mkva0v4ku47v7keu":{"salt":"410ulcaos6mkva0v4ku47v7keu","user_id":"global"},"sh5f3brtj5dn01s9qa5p6s798j":{"salt":"sh5f3brtj5dn01s9qa5p6s798j","user_id":"global"},"ot2eug1h993if50cm7f3aapalk":{"salt":"ot2eug1h993if50cm7f3aapalk","user_id":"global"},"7cctlphmlp3mvhb93p6tqbrs2c":{"salt":"7cctlphmlp3mvhb93p6tqbrs2c","user_id":"global"},"jrhauira2fcvvo60shabuboug5":{"salt":"jrhauira2fcvvo60shabuboug5","user_id":"global"},"21rd1arkov962i8p9s0p2sts22":{"salt":"21rd1arkov962i8p9s0p2sts22","user_id":"global"},"tjubm3citq5t147kpjhk4f18km":{"salt":"tjubm3citq5t147kpjhk4f18km","user_id":"global"},"de8d50dec3fcovfdtjggffb6no":{"salt":"de8d50dec3fcovfdtjggffb6no","user_id":"global"},"2hlumvs23rm9l87uj7dm451rc5":{"salt":"2hlumvs23rm9l87uj7dm451rc5","user_id":"global"},"5un0f1sasrqji0elu9q5rplnjt":{"salt":"5un0f1sasrqji0elu9q5rplnjt","user_id":"global"},"4echbrsv8blsr06jae8hvsrl1d":{"salt":"4echbrsv8blsr06jae8hvsrl1d","user_id":"global"},"ft5vh0lumehn10s1noef0a22i3":{"salt":"ft5vh0lumehn10s1noef0a22i3","user_id":"global"},"0avqg55jkhteglkun8jm3ke16h":{"salt":"0avqg55jkhteglkun8jm3ke16h","user_id":"global"},"e7fqnqik7fr7eeh4fqe1bfkht6":{"salt":"e7fqnqik7fr7eeh4fqe1bfkht6","user_id":"global"},"apvl5d7agv7t6nlc2cuennf27e":{"salt":"apvl5d7agv7t6nlc2cuennf27e","user_id":"global"},"bojkru0vb9smcnu7pt9fghpvqv":{"salt":"bojkru0vb9smcnu7pt9fghpvqv","user_id":"global"},"jbuj8qcbu1f5avmav9a49fpmvq":{"salt":"jbuj8qcbu1f5avmav9a49fpmvq","user_id":"global"},"lc2isa6smv3i2127v5atdnusi5":{"salt":"lc2isa6smv3i2127v5atdnusi5","user_id":"global"},"n58tud8c69s1a1q5n4vt8pibak":{"salt":"n58tud8c69s1a1q5n4vt8pibak","user_id":"global"},"pfsqnl0lqdbi34qg20o9741fti":{"salt":"pfsqnl0lqdbi34qg20o9741fti","user_id":"global"},"vji5uti1ero7vjhg0672djdome":{"salt":"vji5uti1ero7vjhg0672djdome","user_id":"global"},"p5780pdg48ocd72v9gq8kvuc30":{"salt":"p5780pdg48ocd72v9gq8kvuc30","user_id":"global"},"2u1pph7t4n1ijr27o4slnjk2lp":{"salt":"2u1pph7t4n1ijr27o4slnjk2lp","user_id":"global"},"ltk26rak6aeibjqp66kou4lf0g":{"salt":"ltk26rak6aeibjqp66kou4lf0g","user_id":"global"},"46ran4354tocse1j09ic8bm4th":{"salt":"46ran4354tocse1j09ic8bm4th","user_id":"global"},"l78kuqpo6l2jujpf4v0jes2svk":{"salt":"l78kuqpo6l2jujpf4v0jes2svk","user_id":"global"},"c14vfeotatj77kngqajk13e1k3":{"salt":"c14vfeotatj77kngqajk13e1k3","user_id":"global"},"jak1at4sal6futhdjgf5s9fap3":{"salt":"jak1at4sal6futhdjgf5s9fap3","user_id":"global"},"8b2nhp42shn1ps3228dn3c123t":{"salt":"8b2nhp42shn1ps3228dn3c123t","user_id":"global"},"7scec57605ui7aq37p90dq123j":{"salt":"7scec57605ui7aq37p90dq123j","user_id":"global"},"jt4eic0e6bdipm4sumjro5jsdd":{"salt":"jt4eic0e6bdipm4sumjro5jsdd","user_id":"global"},"dr6np4b9v2adu2gko16440rvt1":{"salt":"dr6np4b9v2adu2gko16440rvt1","user_id":"global"},"rnmbe9nrtd9oftsapq4an1fc78":{"salt":"rnmbe9nrtd9oftsapq4an1fc78","user_id":"global"},"vdgl516mtkmmfmh4eooctkd2tk":{"salt":"vdgl516mtkmmfmh4eooctkd2tk","user_id":"global"},"ae3vcfnlh2h9k53k235a44qb3n":{"salt":"ae3vcfnlh2h9k53k235a44qb3n","user_id":"global"},"7g1voku41d3kebm76l24jq3om7":{"salt":"7g1voku41d3kebm76l24jq3om7","user_id":"global"},"1t0o1275im056epeghib4an7u7":{"salt":"1t0o1275im056epeghib4an7u7","user_id":"global"},"vj62rv3t8bbscql4rk2vm25v2e":{"salt":"vj62rv3t8bbscql4rk2vm25v2e","user_id":"global"},"bsk3rc5bsd4bcrqo5vtomnmu5m":{"salt":"bsk3rc5bsd4bcrqo5vtomnmu5m","user_id":"global"},"b4ema8mfn3bkep1a3eh1e8mkss":{"salt":"b4ema8mfn3bkep1a3eh1e8mkss","user_id":"global"},"u1tlm36a63e927ugl5uummdbqa":{"salt":"u1tlm36a63e927ugl5uummdbqa","user_id":"global"},"upoj192njtar36e3nvhvr9d1e3":{"salt":"upoj192njtar36e3nvhvr9d1e3","user_id":"global"},"lrucl49os14qcaqijviag51pf9":{"salt":"lrucl49os14qcaqijviag51pf9","user_id":"global"},"tk722ferbiappao2gm6nehpvsd":{"salt":"tk722ferbiappao2gm6nehpvsd","user_id":"global"},"amierlc00ie7vd0jan2aj7q80o":{"salt":"amierlc00ie7vd0jan2aj7q80o","user_id":"global"},"vec0eegqb3v2v8u8nu0rkn3f65":{"salt":"vec0eegqb3v2v8u8nu0rkn3f65","user_id":"global"},"7ecesj3d73bbn4fmfv84ma10u2":{"salt":"7ecesj3d73bbn4fmfv84ma10u2","user_id":"global"},"257rb48ca55vji6air8k4jmqut":{"salt":"257rb48ca55vji6air8k4jmqut","user_id":"global"},"msgfsmb82pof7adkrdkqdbhgej":{"salt":"msgfsmb82pof7adkrdkqdbhgej","user_id":"global"},"aet7t2iubdrdtr1qd37c9j2b4c":{"salt":"aet7t2iubdrdtr1qd37c9j2b4c","user_id":"global"},"2lf7ahl9br7370smljg1qs0tov":{"salt":"2lf7ahl9br7370smljg1qs0tov","user_id":"global"},"3ojsitdg5f3vflrsqr382sh1rr":{"salt":"3ojsitdg5f3vflrsqr382sh1rr","user_id":"global"},"vk4sfbgqnmh9i0vsf0d7sesa9l":{"salt":"vk4sfbgqnmh9i0vsf0d7sesa9l","user_id":"global"},"o2mpf1bma6o2qun2qrftfu6cla":{"salt":"o2mpf1bma6o2qun2qrftfu6cla","user_id":"global"},"t1850gk1pjf65itnsl9ri4g1en":{"salt":"t1850gk1pjf65itnsl9ri4g1en","user_id":"global"},"g96huco9q15ljq53bncbn40e0p":{"salt":"g96huco9q15ljq53bncbn40e0p","user_id":"global"},"qlcl3g3s9ca030m2a80n5ou0qi":{"salt":"qlcl3g3s9ca030m2a80n5ou0qi","user_id":"global"},"nosk7skgd857orb56aec5istpp":{"salt":"nosk7skgd857orb56aec5istpp","user_id":"global"},"o2lej6uj8t9n5h0g087nqsk8hu":{"salt":"o2lej6uj8t9n5h0g087nqsk8hu","user_id":"global"},"6vquu9p4sit16a7eam31jkrdn4":{"salt":"6vquu9p4sit16a7eam31jkrdn4","user_id":"global"},"4lgf42gfi97cc2b2dsod3136uk":{"salt":"4lgf42gfi97cc2b2dsod3136uk","user_id":"global"},"rnhr4vgrmdgakqeb886bvamn8p":{"salt":"rnhr4vgrmdgakqeb886bvamn8p","user_id":"global"},"cb3i84cmfp3a4qcpsif018vhrd":{"salt":"cb3i84cmfp3a4qcpsif018vhrd","user_id":"global"},"7f1olhkueuesnrjqkvgma5mljj":{"salt":"7f1olhkueuesnrjqkvgma5mljj","user_id":"global"},"5ab7fj2vjb0q3vcq7ooduprofr":{"salt":"5ab7fj2vjb0q3vcq7ooduprofr","user_id":"global"},"heau3ie3hslpbi1r80mne7fh71":{"salt":"heau3ie3hslpbi1r80mne7fh71","user_id":"global"},"b3jo0to0p7ie3n8qjbc5bir6e6":{"salt":"b3jo0to0p7ie3n8qjbc5bir6e6","user_id":"global"},"qgpvcj5bi8h0t0dc97edog7ams":{"salt":"qgpvcj5bi8h0t0dc97edog7ams","user_id":"global"},"d5r6cjukdj31aepu9c9dpkn103":{"salt":"d5r6cjukdj31aepu9c9dpkn103","user_id":"global"},"08322blr2naigugdbjrha1dpvs":{"salt":"08322blr2naigugdbjrha1dpvs","user_id":"global"},"t4krbutqe7kam6h14it4taj3pl":{"salt":"t4krbutqe7kam6h14it4taj3pl","user_id":"global"},"2vu9170jcu5i5d4t16vjkf4qau":{"salt":"2vu9170jcu5i5d4t16vjkf4qau","user_id":"global"},"93he8hca2b56gcvk374m7ch8jq":{"salt":"93he8hca2b56gcvk374m7ch8jq","user_id":"global"},"rb41d5j0dj1bta5srp935466fj":{"salt":"rb41d5j0dj1bta5srp935466fj","user_id":"global"},"l31q1v56a93l5g6ncfsr1kqqa1":{"salt":"l31q1v56a93l5g6ncfsr1kqqa1","user_id":"global"},"kafge8kbsf17e6dicivchn700r":{"salt":"kafge8kbsf17e6dicivchn700r","user_id":"global"},"qrojoc0v9k6e08i7h37dcrc2kr":{"salt":"qrojoc0v9k6e08i7h37dcrc2kr","user_id":"global"},"u5s1sq663sci37bgfhc4s8s5sl":{"salt":"u5s1sq663sci37bgfhc4s8s5sl","user_id":"global"},"b9sum1lg4s11a3alp3mrgde0dj":{"salt":"b9sum1lg4s11a3alp3mrgde0dj","user_id":"global"},"8eu869k24nt0iqp3mb1i5egq79":{"salt":"8eu869k24nt0iqp3mb1i5egq79","user_id":"global"},"3as7l1nom6i47jias7u84oq70q":{"salt":"3as7l1nom6i47jias7u84oq70q","user_id":"global"},"t64gj7aup2hp10dhlm5ugob7lh":{"salt":"t64gj7aup2hp10dhlm5ugob7lh","user_id":"global"},"0qr7ei8b1h7v8755lr9gfcou8h":{"salt":"0qr7ei8b1h7v8755lr9gfcou8h","user_id":"global"},"p6o9ps1gkkjasuubv7165uenqb":{"salt":"p6o9ps1gkkjasuubv7165uenqb","user_id":"global"},"29j6br1bb1926a6epcqj31kpch":{"salt":"29j6br1bb1926a6epcqj31kpch","user_id":"global"},"2099m1dm2o45j8f5g0idbt2jh6":{"salt":"2099m1dm2o45j8f5g0idbt2jh6","user_id":"global"},"v3vnhvolbmmhgk5fmaltbp0nmc":{"salt":"v3vnhvolbmmhgk5fmaltbp0nmc","user_id":"global"},"71d3ov446fodo9mh9k8b17oi2s":{"salt":"71d3ov446fodo9mh9k8b17oi2s","user_id":"global"},"b23le4rta59ts6dmtjvs35g1hn":{"salt":"b23le4rta59ts6dmtjvs35g1hn","user_id":"global"},"177t0iiar4cni6dafjjcomdmg9":{"salt":"177t0iiar4cni6dafjjcomdmg9","user_id":"global"},"4ikhm3m5jf9i18ur2nnsplrakf":{"salt":"4ikhm3m5jf9i18ur2nnsplrakf","user_id":"global"},"cliqc4n3suf17ls8o0plpccnv3":{"salt":"cliqc4n3suf17ls8o0plpccnv3","user_id":"global"},"h5brf7hvcg85s225eveqldc0ia":{"salt":"h5brf7hvcg85s225eveqldc0ia","user_id":"global"},"asoo3bfq357b7qagke02kotd9i":{"salt":"asoo3bfq357b7qagke02kotd9i","user_id":"global"},"060p4n5kvrfcvkjh0bfnji06bk":{"salt":"060p4n5kvrfcvkjh0bfnji06bk","user_id":"global"},"it9vasi70h8f66r15e969e2odv":{"salt":"it9vasi70h8f66r15e969e2odv","user_id":"global"},"6cc5adq9gefoleh14b5bb9e007":{"salt":"6cc5adq9gefoleh14b5bb9e007","user_id":"global"},"nq9jp2sgpq7ljvehle51ud59av":{"salt":"nq9jp2sgpq7ljvehle51ud59av","user_id":"global"},"k619cfh72fahkta18fsvptri0m":{"salt":"k619cfh72fahkta18fsvptri0m","user_id":"global"},"4m5aandfj3fhfalrpev79r7lpu":{"salt":"4m5aandfj3fhfalrpev79r7lpu","user_id":"global"},"0dn5tvvo7hdb3odd1qa0maec39":{"salt":"0dn5tvvo7hdb3odd1qa0maec39","user_id":"global"},"q4u3t3edt5pqg74o8j3so7ctq8":{"salt":"q4u3t3edt5pqg74o8j3so7ctq8","user_id":"global"},"mdgefk4qvsucnapnujn3f2dn5g":{"salt":"mdgefk4qvsucnapnujn3f2dn5g","user_id":"global"},"tenrnc0lp1mn8t5abufoe070bc":{"salt":"tenrnc0lp1mn8t5abufoe070bc","user_id":"global"},"c5cp06r42b3jo3735a4m4cs1pg":{"salt":"c5cp06r42b3jo3735a4m4cs1pg","user_id":"global"},"c51mpv59qpqa8r91fvjmj1oo07":{"salt":"c51mpv59qpqa8r91fvjmj1oo07","user_id":"global"},"iv66lupfe0bf3lr8sibdjgphu1":{"salt":"iv66lupfe0bf3lr8sibdjgphu1","user_id":"global"},"km5j8etjnjodahihmt9ot1crlc":{"salt":"km5j8etjnjodahihmt9ot1crlc","user_id":"global"},"uo04fbpt8clmndkp63bfomh6im":{"salt":"uo04fbpt8clmndkp63bfomh6im","user_id":"global"}}